Metadata-Version: 1.0
Name: tsbfpackage
Version: 0.1
Summary: TSBs First Package
Home-page: UNKNOWN
Author: Karthik Thirukonda
Author-email: UNKNOWN
License: UNKNOWN
Platform: UNKNOWN
